metabase_data_api/__init__.py
metabase_data_api/metabase_data_api.py
metabase_data_api-0.1.11.dist-info/LICENSE.txt
metabase_data_api-0.1.11.dist-info/WHEEL
metabase_data_api-0.1.11.dist-info/METADATA
metabase_data_api-0.1.11.dist-info/RECORD
