Metadata-Version: 2.1
Name: metabase-data-api
Version: 0.1.11
Summary: A package for querying metabase data via api.
Home-page: https://github.com/scale-vector/metabase_data_api
License: MIT
Keywords: metabase
Author: Adrian Brudaru
Author-email: adrian@scalevector.ai
Requires-Python: >=3.7,<4.0
Classifier: License :: OSI Approved :: MIT License
Classifier: Programming Language :: Python :: 3
Classifier: Programming Language :: Python :: 3.10
Classifier: Programming Language :: Python :: 3.7
Classifier: Programming Language :: Python :: 3.8
Classifier: Programming Language :: Python :: 3.9
Requires-Dist: requests (>=2.23.0,<3.0.0)
Project-URL: Repository, https://github.com/scale-vector/metabase_data_api
